fluidize_sdk/__init__.py
fluidize_sdk/_base_client.py
fluidize_sdk/_client.py
fluidize_sdk/_compat.py
fluidize_sdk/_constants.py
fluidize_sdk/_exceptions.py
fluidize_sdk/_files.py
fluidize_sdk/_models.py
fluidize_sdk/_qs.py
fluidize_sdk/_resource.py
fluidize_sdk/_response.py
fluidize_sdk/_streaming.py
fluidize_sdk/_types.py
fluidize_sdk/_version.py
fluidize_sdk/py.typed
fluidize_sdk/_utils/__init__.py
fluidize_sdk/_utils/_logs.py
fluidize_sdk/_utils/_proxy.py
fluidize_sdk/_utils/_reflection.py
fluidize_sdk/_utils/_resources_proxy.py
fluidize_sdk/_utils/_streams.py
fluidize_sdk/_utils/_sync.py
fluidize_sdk/_utils/_transform.py
fluidize_sdk/_utils/_typing.py
fluidize_sdk/_utils/_utils.py
fluidize_sdk/lib/.keep
fluidize_sdk/resources/__init__.py
fluidize_sdk/resources/candy.py
fluidize_sdk/resources/files.py
fluidize_sdk/resources/graph.py
fluidize_sdk/resources/list_environments.py
fluidize_sdk/resources/projects.py
fluidize_sdk/resources/simulation.py
fluidize_sdk/resources/test_connection.py
fluidize_sdk/resources/upsert_simulation.py
fluidize_sdk/resources/auth/__init__.py
fluidize_sdk/resources/auth/auth.py
fluidize_sdk/resources/auth/ssh.py
fluidize_sdk/resources/runs/__init__.py
fluidize_sdk/resources/runs/logs.py
fluidize_sdk/resources/runs/runs.py
fluidize_sdk/resources/utils/__init__.py
fluidize_sdk/resources/utils/retrieval_mode.py
fluidize_sdk/resources/utils/utils.py
fluidize_sdk/types/__init__.py
fluidize_sdk/types/auth_session_login_params.py
fluidize_sdk/types/auth_session_login_response.py
fluidize_sdk/types/file_get_project_node_path_params.py
fluidize_sdk/types/file_get_project_node_path_response.py
fluidize_sdk/types/file_get_simulation_path_params.py
fluidize_sdk/types/file_get_simulation_path_response.py
fluidize_sdk/types/file_list_directory_response.py
fluidize_sdk/types/file_load_editor_file_response.py
fluidize_sdk/types/file_save_editor_file_params.py
fluidize_sdk/types/file_save_file_content_params.py
fluidize_sdk-0.9.0.dist-info/METADATA
fluidize_sdk-0.9.0.dist-info/WHEEL
fluidize_sdk-0.9.0.dist-info/licenses/LICENSE
fluidize_sdk-0.9.0.dist-info/RECORD
